[
	{
		"__TYPE__": "SharedSliceContent",
		"variation": "default",
		"primary": {
			"header": {
				"__TYPE__": "FieldContent",
				"value": "bar",
				"type": "Text"
			},
			"description": {
				"__TYPE__": "StructuredTextContent",
				"value": [
					{
						"type": "paragraph",
						"content": {
							"text": "Ea consectetur dolor eiusmod officia ut. Nulla elit deserunt do dolore sunt ut officia non laboris mollit Lorem aliquip reprehenderit anim. Irure laboris proident duis occaecat in."
						}
					}
				]
			},
			"image": {
				"origin": {
					"id": "main",
					"url": "https://images.unsplash.com/photo-1560457079-9a6532ccb118",
					"width": 4160,
					"height": 3120
				},
				"url": "https://images.unsplash.com/photo-1560457079-9a6532ccb118",
				"width": 4160,
				"height": 3120,
				"edit": {
					"zoom": 1,
					"crop": {
						"x": 0,
						"y": 0
					},
					"background": "transparent"
				},
				"credits": null,
				"alt": null,
				"__TYPE__": "ImageContent",
				"thumbnails": {}
			},
			"button_text": {
				"__TYPE__": "FieldContent",
				"value": "oil",
				"type": "Text"
			},
			"button_link": {
				"__TYPE__": "LinkContent",
				"value": {
					"__TYPE__": "ExternalLink",
					"url": "http://twitter.com"
				}
			}
		},
		"items": []
	}
]